PyCharmSync/__init__.py
PyCharmSync-0.0.2.dist-info/METADATA
PyCharmSync-0.0.2.dist-info/RECORD
PyCharmSync-0.0.2.dist-info/WHEEL
PyCharmSync-0.0.2.dist-info/top_level.txt
