Metadata-Version: 2.1
Name: PyCharmSync
Version: 0.0.2
Summary: PyCharmSync is a simple tool for uploading changed project files to a remote host, about as soon as they change.
Home-page: https://github.com/Wykleph/PyCharmSync
Author: py-am-i
Author-email: duckpuncherirl@gmail.com
License: UNKNOWN
Platform: UNKNOWN
Classifier: Programming Language :: Python :: 3
Classifier: License :: OSI Approved :: MIT License
Classifier: Operating System :: OS Independent
